{
    "bookTitle": "Zabiják",
    "questions": [
        {
            "id": "druh",
            "type": "mc_single",
            "questionText": "Literární druh:",
            "options": ["Próza", "Poezie", "Drama"],
            "correctAnswer": "Próza"
        },
        {
            "id": "zanr",
            "type": "free_text",
            "questionText": "Literární žánr:",
            "correctAnswer": "Román"
        },
        {
            "id": "tema",
            "type": "mc_single",
            "questionText": "Hlavní téma:",
            "options": ["Alkoholismus a jeho destruktivní vliv", "Sériový vrah", "Hledání smyslu života", "Romantický vztah"],
            "correctAnswer": "Alkoholismus a jeho destruktivní vliv"
        },
        {
            "id": "postavy",
            "type": "mc_multiple",
            "questionText": "Hlavní postavy (vyberte všechny správné):",
            "options": ["Gervaise Macquartová", "Lantier", "Coupeau", "Goujet", "Jean Valjean", "Coupier", "Harry Huesse"],
            "correctAnswers": ["Gervaise Macquartová", "Lantier", "Coupeau", "Goujet"]
        },
        {
            "id": "cas",
            "type": "mc_single",
            "questionText": "Časové zařazení děje:",
            "options": ["19. století", "20. století", "Středověk", "Budoucnost"],
            "correctAnswer": "19. století"
        },
        {
            "id": "prostor",
            "type": "mc_single",
            "questionText": "Místo děje:",
            "options": ["Paříž", "Londýn", "New York", "Berlín"],
            "correctAnswer": "Paříž"
        },
        {
            "id": "kompozice",
            "type": "mc_single",
            "questionText": "Kompozice:",
            "options": ["Chronologická", "Retrospektivní", "Rámcová", "Mozaikovitá"],
            "correctAnswer": "Chronologická"
        },
        {
            "id": "vypravec",
            "type": "mc_single",
            "questionText": "Vypravěč / Forma projevu:",
            "options": ["Ich-forma", "Er-forma", "Monology/Dialogy"],
            "correctAnswer": "Er-forma"
        },
        {
            "id": "smer",
            "type": "mc_single",
            "questionText": "Literární směr:",
            "options": ["Naturalismus", "Romantismus", "Symbolismus", "Realismus"],
            "correctAnswer": "Naturalismus"
        }
    ]
}
