{
    "bookTitle": "Máj",
    "questions": [
        {
            "id": "druh",
            "type": "mc_single",
            "questionText": "Literární druh:",
            "options": ["Próza", "Poezie", "Drama"],
            "correctAnswer": "Poezie"
        },
        {
            "id": "zanr",
            "type": "free_text",
            "questionText": "Literární žánr:",
            "correctAnswer": "lyricko-epická báseň"
        },
        {
            "id": "tema",
            "type": "mc_single",
            "questionText": "Hlavní téma:",
            "options": ["Láska, zrada a trest", "Změna společenských poměrů", "Cesta do neznáma", "Přírodní krásy"],
            "correctAnswer": "Láska, zrada a trest"
        },
        {
            "id": "postavy",
            "type": "mc_multiple",
            "questionText": "Hlavní postavy (vyberte všechny správné):",
            "options": ["Vilém", "Jarmila", "Hynek", "Vilémův otec", "Hynkův otec", "Sládek", "Honza"],
            "correctAnswers": ["Vilém", "Jarmila", "Hynek", "Vilémův otec"]
        },
        {
            "id": "cas",
            "type": "mc_single",
            "questionText": "Časové zařazení děje:",
            "options": ["19. století", "20. století", "Středověk", "Neurčená doba"],
            "correctAnswer": "Neurčená doba"
        },
        {
            "id": "prostor",
            "type": "mc_single",
            "questionText": "Místo děje:",
            "options": ["U jezera", "Praha", "Na zámku", "V hlubokém lese"],
            "correctAnswer": "U jezera"
        },
        {
            "id": "kompozice",
            "type": "mc_single",
            "questionText": "Kompozice:",
            "options": ["Chronologická", "Retrospektivní", "Rámcová", "Mozaikovitá"],
            "correctAnswer": "Chronologická"
        },
        {
            "id": "vypravec",
            "type": "mc_single",
            "questionText": "Vypravěč / Forma projevu:",
            "options": ["Ich-forma", "Er-forma", "Lyrický subjekt"],
            "correctAnswer": "Lyrický subjekt"
        },
        {
            "id": "smer",
            "type": "mc_single",
            "questionText": "Literární směr:",
            "options": ["Romantismus", "Realismus", "Naturalismus", "Symbolismus"],
            "correctAnswer": "Romantismus"
        }
    ]
}
